[
  {
    "idConcert": 1,
    "artiste": "Burna Boy",
    "date": "2025-08-20",
    "nom": "Patrick armel",
    "email": "mokepatrifi@gmail.com",
    "quantite": "1",
    "timestamp": "2025-07-14T18:51:20.746Z"
  },
  {
    "idConcert": 2,
    "artiste": "Aya Nakamura",
    "date": "2025-09-05",
    "nom": "Moke",
    "email": "thesouscote@gmail.com",
    "quantite": "1",
    "timestamp": "2025-07-14T18:57:10.069Z"
  },
  {
    "idConcert": 1,
    "artiste": "Burna Boy",
    "date": "2025-08-20",
    "nom": "Patrick armel",
    "email": "mokepatrifi@gmail.com",
    "quantite": "1",
    "timestamp": "2025-07-14T19:02:12.607Z"
  },
  {
    "idConcert": 1,
    "artiste": "Burna Boy",
    "date": "2025-08-20",
    "nom": "Moke Patrick Armel ",
    "email": "mokepatrickarmel@gmail.com",
    "quantite": "1",
    "timestamp": "2025-07-14T19:02:39.940Z"
  },
  {
    "idConcert": 1,
    "artiste": "Burna Boy",
    "date": "2025-08-20",
    "nom": "Patrick armel",
    "email": "mokepatrickarmel@gmail.com",
    "quantite": "1",
    "timestamp": "2025-07-14T19:03:32.004Z"
  },
  {
    "idConcert": 1,
    "artiste": "Burna Boy",
    "date": "2025-08-20",
    "nom": "Patrick ",
    "email": "thesouscote@gmail.com",
    "quantite": "1",
    "timestamp": "2025-07-14T19:08:09.354Z"
  },
  {
    "idConcert": 2,
    "artiste": "Aya Nakamura",
    "date": "2025-09-05",
    "nom": "Husi",
    "email": "mokepatrickarmel@gmail.com",
    "quantite": "1",
    "timestamp": "2025-07-14T19:10:49.423Z"
  },
  {
    "idConcert": 1,
    "artiste": "Burna Boy",
    "date": "2025-08-20",
    "nom": "moke",
    "email": "mokepatrickarmel@gmail.com",
    "quantite": "1",
    "timestamp": "2025-07-14T19:26:26.005Z"
  },
  {
    "idConcert": 1,
    "artiste": "Burna Boy",
    "date": "2025-08-20",
    "nom": "Bjonea",
    "email": "mokepatrickarmel@gmail.com",
    "quantite": "1",
    "timestamp": "2025-07-14T19:27:23.238Z"
  },
  {
    "idConcert": 1,
    "artiste": "Burna Boy",
    "date": "2025-08-20",
    "nom": "Bonjour ",
    "email": "moke@gmail.com",
    "quantite": "1",
    "timestamp": "2025-07-14T19:34:56.142Z"
  },
  {
    "idConcert": 1,
    "artiste": "Burna Boy",
    "date": "2025-08-20",
    "nom": "Bonjour ",
    "email": "moke@gmail.com",
    "quantite": "1",
    "timestamp": "2025-07-14T19:36:23.075Z"
  },
  {
    "idConcert": 2,
    "artiste": "Aya Nakamura",
    "date": "2025-09-05",
    "nom": "TONY",
    "email": "tony@gmail.com",
    "quantite": "1",
    "timestamp": "2025-07-14T19:36:42.340Z"
  },
  {
    "idConcert": 2,
    "artiste": "Aya Nakamura",
    "date": "2025-09-05",
    "nom": "Konan",
    "email": "koy@gmail.com",
    "quantite": "1",
    "timestamp": "2025-07-14T19:40:35.285Z"
  },
  {
    "idConcert": 1,
    "artiste": "Burna Boy",
    "date": "2025-08-20",
    "nom": "damso",
    "email": "enni@gmail.com",
    "quantite": "1",
    "timestamp": "2025-07-14T19:42:25.886Z"
  },
  {
    "idConcert": 2,
    "artiste": "Aya Nakamura",
    "date": "2025-09-05",
    "nom": "TONY",
    "email": "tony@gmail.com",
    "quantite": "1",
    "timestamp": "2025-07-14T19:45:52.928Z"
  },
  {
    "idConcert": 2,
    "artiste": "Aya Nakamura",
    "date": "2025-09-05",
    "nom": "gossel",
    "email": "giskk@gmail.com",
    "quantite": "1",
    "timestamp": "2025-07-14T19:46:13.090Z"
  },
  {
    "idConcert": 1,
    "artiste": "Burna Boy",
    "date": "2025-08-20",
    "nom": "Ggfsse",
    "email": "chhhg@gl",
    "quantite": "1",
    "timestamp": "2025-07-14T19:49:27.005Z"
  },
  {
    "idConcert": 2,
    "artiste": "Aya Nakamura",
    "date": "2025-09-05",
    "nom": "jshshh",
    "email": "667@gmail.com",
    "quantite": "1",
    "timestamp": "2025-07-14T19:53:20.871Z"
  }
]